[
    {
        "x": 327.33143156127454,
        "y": 493.2199330851293,
        "radius": 21
    },
    {
        "x": 362.8132001757262,
        "y": 508.2252069880708,
        "radius": 21
    },
    {
        "x": 474.0576499963224,
        "y": 554.124564086397,
        "radius": 21
    },
    {
        "x": 516.9284644711262,
        "y": 567.3679200111288,
        "radius": 21
    },
    {
        "x": 542.8873067605987,
        "y": 579.050585467826,
        "radius": 21
    },
    {
        "x": 580.8269802114464,
        "y": 594.2560583662798,
        "radius": 21
    },
    {
        "x": 649.7235312950779,
        "y": 623.6263518372723,
        "radius": 21
    },
    {
        "x": 686.7232329825501,
        "y": 636.1976251884182,
        "radius": 21
    },
    {
        "x": 795.2737149670061,
        "y": 677.8459080135997,
        "radius": 21
    },
    {
        "x": 723.8662264760377,
        "y": 648.9731615209633,
        "radius": 21
    },
    {
        "x": 759.4132484496206,
        "y": 663.9437331616792,
        "radius": 21
    },
    {
        "x": 833.2877086654296,
        "y": 687.3245886492515,
        "radius": 21
    },
    {
        "x": 522.9455324979501,
        "y": 526.288742675559,
        "radius": 21
    },
    {
        "x": 810.7738137520394,
        "y": 636.7653940628012,
        "radius": 21
    },
    {
        "x": 250.49261958141773,
        "y": 372.53757089674315,
        "radius": 21
    },
    {
        "x": 353.4779902455475,
        "y": 416.84595080413163,
        "radius": 21
    },
    {
        "x": 390.0358132797132,
        "y": 428.62076546009246,
        "radius": 21
    },
    {
        "x": 754.440949736027,
        "y": 570.8618896185669,
        "radius": 21
    },
    {
        "x": 792.161734705319,
        "y": 585.274835400533,
        "radius": 21
    },
    {
        "x": 828.3291041114123,
        "y": 595.633217715002,
        "radius": 21
    },
    {
        "x": 942.0524310600275,
        "y": 639.2512406188581,
        "radius": 21
    },
    {
        "x": 189.41806439097763,
        "y": 309.5261061140004,
        "radius": 21
    },
    {
        "x": 226.3004134781279,
        "y": 323.3885592822659,
        "radius": 21
    },
    {
        "x": 365.88755593133016,
        "y": 378.37838408136554,
        "radius": 21
    },
    {
        "x": 406.0041553614362,
        "y": 386.263947428215,
        "radius": 21
    },
    {
        "x": 437.74417519341307,
        "y": 399.29724798083373,
        "radius": 21
    },
    {
        "x": 688.6596122296751,
        "y": 504.53465562752416,
        "radius": 21
    },
    {
        "x": 619.7988053489661,
        "y": 473.5409306296333,
        "radius": 21
    },
    {
        "x": 727.0423216675176,
        "y": 516.7726369821871,
        "radius": 21
    },
    {
        "x": 552.7401166943993,
        "y": 443.38599296518254,
        "radius": 21
    },
    {
        "x": 769.0323340786047,
        "y": 534.630188973037,
        "radius": 21
    },
    {
        "x": 808.2755311851241,
        "y": 542.6959605549064,
        "radius": 21
    },
    {
        "x": 919.1909355680692,
        "y": 586.8649163912827,
        "radius": 21
    },
    {
        "x": 959.4351654664508,
        "y": 602.0344001214501,
        "radius": 21
    },
    {
        "x": 275.77364220482235,
        "y": 298.5033927893345,
        "radius": 21
    },
    {
        "x": 168.46496454801752,
        "y": 254.8006520720514,
        "radius": 21
    },
    {
        "x": 205.81315075409987,
        "y": 268.2918675373141,
        "radius": 21
    },
    {
        "x": 312.12939649589305,
        "y": 311.46179987912865,
        "radius": 21
    },
    {
        "x": 382.1021140779146,
        "y": 335.1420799930114,
        "radius": 21
    },
    {
        "x": 420.9401383707818,
        "y": 349.64613879426827,
        "radius": 21
    },
    {
        "x": 644.237686368141,
        "y": 437.7319888094317,
        "radius": 21
    },
    {
        "x": 787.3398511637556,
        "y": 498.0747471544014,
        "radius": 21
    },
    {
        "x": 563.8521211642017,
        "y": 401.62649090315705,
        "radius": 21
    },
    {
        "x": 826.3374848821414,
        "y": 503.6223290728898,
        "radius": 21
    },
    {
        "x": 864.4303670779458,
        "y": 518.9131861980807,
        "radius": 21
    },
    {
        "x": 901.7123124027167,
        "y": 534.3964534562926,
        "radius": 21
    },
    {
        "x": 938.4130268555249,
        "y": 547.9792664251701,
        "radius": 21
    },
    {
        "x": 143.78104712773978,
        "y": 201.36159302831214,
        "radius": 21
    },
    {
        "x": 291.4989498692163,
        "y": 256.3340453787886,
        "radius": 21
    },
    {
        "x": 396.1717722314962,
        "y": 294.60807449129425,
        "radius": 21
    },
    {
        "x": 657.7034890618188,
        "y": 395.8662892964214,
        "radius": 21
    },
    {
        "x": 619.559127121433,
        "y": 379.3326923214205,
        "radius": 21
    },
    {
        "x": 840.0727550574131,
        "y": 466.24538807289855,
        "radius": 21
    },
    {
        "x": 800.6405773191979,
        "y": 449.8707443844388,
        "radius": 21
    },
    {
        "x": 197.59076202131104,
        "y": 175.66743211280578,
        "radius": 21
    },
    {
        "x": 270.8250623158691,
        "y": 202.69184810850737,
        "radius": 21
    },
    {
        "x": 307.37928662679434,
        "y": 217.46791905225868,
        "radius": 21
    },
    {
        "x": 236.5459054247346,
        "y": 188.09241632237575,
        "radius": 21
    },
    {
        "x": 452.64129756907573,
        "y": 269.84719093199647,
        "radius": 21
    },
    {
        "x": 418.5784314011293,
        "y": 253.6228155648585,
        "radius": 21
    },
    {
        "x": 490.0115060068141,
        "y": 282.2248475199532,
        "radius": 21
    },
    {
        "x": 638.0044337976431,
        "y": 340.29172755079594,
        "radius": 21
    },
    {
        "x": 676.2216248730526,
        "y": 355.95915345786926,
        "radius": 21
    },
    {
        "x": 968.057843178538,
        "y": 470.74011371492253,
        "radius": 21
    },
    {
        "x": 852.3572114760286,
        "y": 423.54753927662625,
        "radius": 21
    },
    {
        "x": 1003.603611677036,
        "y": 486.2797879039791,
        "radius": 21
    },
    {
        "x": 322.56150699786167,
        "y": 178.24779492200574,
        "radius": 21
    },
    {
        "x": 499.5394458641598,
        "y": 243.2681759257068,
        "radius": 21
    },
    {
        "x": 426.7790043349732,
        "y": 213.5491456794758,
        "radius": 21
    },
    {
        "x": 463.9355202511118,
        "y": 227.48090847906036,
        "radius": 21
    },
    {
        "x": 647.7373748350446,
        "y": 303.34571418934127,
        "radius": 21
    },
    {
        "x": 687.0635291321531,
        "y": 316.42421794130837,
        "radius": 21
    },
    {
        "x": 1010.2608708134771,
        "y": 448.3348456003648,
        "radius": 21
    },
    {
        "x": 944.9650777883986,
        "y": 417.2928858238413,
        "radius": 21
    },
    {
        "x": 981.1641477939775,
        "y": 433.2841503519096,
        "radius": 21
    },
    {
        "x": 754.2566692112907,
        "y": 337.63151383283946,
        "radius": 21
    },
    {
        "x": 905.6040433856274,
        "y": 399.65205587321213,
        "radius": 21
    },
    {
        "x": 792.5405039756876,
        "y": 350.3721483180093,
        "radius": 21
    },
    {
        "x": 187.22303263366837,
        "y": 78.88836135698304,
        "radius": 21
    },
    {
        "x": 378.03465343536965,
        "y": 157.92716605886181,
        "radius": 21
    },
    {
        "x": 266.4473127073854,
        "y": 110.52953399266586,
        "radius": 21
    },
    {
        "x": 340.4865453518063,
        "y": 140.7398437674825,
        "radius": 21
    },
    {
        "x": 667.8062023592806,
        "y": 263.40820281159847,
        "radius": 21
    },
    {
        "x": 771.3940548358656,
        "y": 297.52893687250133,
        "radius": 21
    },
    {
        "x": 957.6811255410303,
        "y": 375.181290286328,
        "radius": 21
    },
    {
        "x": 278.4286332475448,
        "y": 72.35217948008162,
        "radius": 21
    },
    {
        "x": 850.6794355594828,
        "y": 326.2873356316894,
        "radius": 21
    },
    {
        "x": 315.78691074115306,
        "y": 85.5655334849023,
        "radius": 21
    },
    {
        "x": 390.2181996253365,
        "y": 118.06933040080337,
        "radius": 21
    },
    {
        "x": 352.43476509279026,
        "y": 100.57560031929677,
        "radius": 21
    },
    {
        "x": 407.66194374197175,
        "y": 76.05066274575408,
        "radius": 21
    },
    {
        "x": 473.1510793824782,
        "y": 95.704841954778,
        "radius": 21
    },
    {
        "x": 509.1042154984069,
        "y": 107.5372924916127,
        "radius": 21
    },
    {
        "x": 547.025716420163,
        "y": 118.86705201829469,
        "radius": 21
    },
    {
        "x": 660.5046761940856,
        "y": 164.16636759380378,
        "radius": 21
    },
    {
        "x": 697.1951734804423,
        "y": 180.63853207696064,
        "radius": 21
    },
    {
        "x": 913.1975086577472,
        "y": 271.15971402693947,
        "radius": 21
    },
    {
        "x": 948.9752577289853,
        "y": 285.890609106491,
        "radius": 21
    },
    {
        "x": 984.2761826578073,
        "y": 300.87921795454804,
        "radius": 21
    },
    {
        "x": 735.8284706567637,
        "y": 196.86482014978023,
        "radius": 21
    },
    {
        "x": 876.3713570342696,
        "y": 254.6887665063924,
        "radius": 21
    },
    {
        "x": 803.2641060977239,
        "y": 222.6737767808497,
        "radius": 21
    },
    {
        "x": 841.556328675474,
        "y": 239.0145679947105,
        "radius": 21
    },
    {
        "x": 384.1503298922223,
        "y": 27.473333655036882,
        "radius": 21
    },
    {
        "x": 485.99942792246406,
        "y": 55.10232600096013,
        "radius": 21
    },
    {
        "x": 960.4205299639211,
        "y": 245.05649338091214,
        "radius": 21
    },
    {
        "x": 749.6613038965728,
        "y": 155.76453494218939,
        "radius": 21
    },
    {
        "x": 883.8867717479964,
        "y": 211.85118430463052,
        "radius": 21
    },
    {
        "x": 674.9558565285294,
        "y": 120.14692634688888,
        "radius": 21
    },
    {
        "x": 598.4314547863562,
        "y": 89.41973073852519,
        "radius": 21
    },
    {
        "x": 922.2797765735515,
        "y": 228.5840684634772,
        "radius": 21
    },
    {
        "x": 638.8764108410868,
        "y": 102.48389168180128,
        "radius": 21
    },
    {
        "x": 442.9924008626208,
        "y": 3.5501052901905297,
        "radius": 21
    },
    {
        "x": 690.4720475922164,
        "y": 73.70133462478336,
        "radius": 21
    },
    {
        "x": 763.598176156659,
        "y": 113.43503804002836,
        "radius": 21
    },
    {
        "x": 864.5854034674404,
        "y": 157.18082139703165,
        "radius": 21
    },
    {
        "x": 613.6159936651021,
        "y": 44.730267213640104,
        "radius": 21
    },
    {
        "x": 651.8626190482183,
        "y": 61.594913962031825,
        "radius": 21
    },
    {
        "x": 992.4318841726868,
        "y": 397.11836914135006,
        "radius": 21
    },
    {
        "x": 925.7476300418067,
        "y": 360.98378668938415,
        "radius": 21
    },
    {
        "x": 891.1022858047945,
        "y": 346.1992613054149,
        "radius": 21
    },
    {
        "x": 814.5178406492944,
        "y": 313.51767887769347,
        "radius": 21
    },
    {
        "x": 902.7291376823243,
        "y": 174.5715103267212,
        "radius": 21
    },
    {
        "x": 940.6490124967681,
        "y": 191.85023463830015,
        "radius": 21
    },
    {
        "x": 830.3309426894405,
        "y": 144.77319328408234,
        "radius": 21
    },
    {
        "x": 932.2232686799517,
        "y": 454.7839585563831,
        "radius": 21
    },
    {
        "x": 780.4671701298519,
        "y": 396.60465811714096,
        "radius": 21
    },
    {
        "x": 745.8218258928398,
        "y": 381.8201327331717,
        "radius": 21
    },
    {
        "x": 847.0152279256116,
        "y": 556.6227376550164,
        "radius": 21
    },
    {
        "x": 879.8371329922545,
        "y": 570.6291301240399,
        "radius": 21
    },
    {
        "x": 988.777533909238,
        "y": 527.1783314538143,
        "radius": 21
    },
    {
        "x": 978.4422213029097,
        "y": 566.6409876499068,
        "radius": 21
    },
    {
        "x": 949.5735917463032,
        "y": 510.44847378248056,
        "radius": 21
    },
    {
        "x": 913.8495038655349,
        "y": 493.0099492881292,
        "radius": 21
    },
    {
        "x": 879.7435314504011,
        "y": 479.5524234593511,
        "radius": 21
    },
    {
        "x": 759.6922946770254,
        "y": 438.19331478228696,
        "radius": 21
    },
    {
        "x": 718.8319374022935,
        "y": 422.95025684891687,
        "radius": 21
    },
    {
        "x": 707.3795815060466,
        "y": 465.22671233816413,
        "radius": 21
    },
    {
        "x": 743.8483649134276,
        "y": 480.7893706370792,
        "radius": 21
    },
    {
        "x": 718.2467940115424,
        "y": 558.7072838396183,
        "radius": 21
    },
    {
        "x": 683.6014497745305,
        "y": 543.922758455649,
        "radius": 21
    },
    {
        "x": 773.5552915385001,
        "y": 626.1827249737579,
        "radius": 21
    },
    {
        "x": 742.9291734055323,
        "y": 612.0165323219619,
        "radius": 21
    },
    {
        "x": 703.5199075378636,
        "y": 598.4895404012559,
        "radius": 21
    },
    {
        "x": 665.2276849601135,
        "y": 582.1487491873951,
        "radius": 21
    },
    {
        "x": 852.4504225661626,
        "y": 642.3011120080965,
        "radius": 21
    },
    {
        "x": 864.5325750505351,
        "y": 614.5521855340231,
        "radius": 21
    },
    {
        "x": 903.774816859632,
        "y": 625.81424480182,
        "radius": 21
    },
    {
        "x": 885.1957283404809,
        "y": 667.2431012841936,
        "radius": 21
    },
    {
        "x": 927.7125007270095,
        "y": 680.9993594796001,
        "radius": 21
    },
    {
        "x": 873.9486961489681,
        "y": 706.3166910228134,
        "radius": 21
    },
    {
        "x": 893.8927464560393,
        "y": 443.91096574605916,
        "radius": 21
    },
    {
        "x": 870.9050818200086,
        "y": 383.64711912221514,
        "radius": 21
    },
    {
        "x": 829.877700486705,
        "y": 366.1391285359358,
        "radius": 21
    },
    {
        "x": 816.0242339520483,
        "y": 411.77824995858305,
        "radius": 21
    },
    {
        "x": 728.7577209706517,
        "y": 102.52474960231146,
        "radius": 21
    },
    {
        "x": 709.8062846881943,
        "y": 144.89153918240322,
        "radius": 21
    },
    {
        "x": 576.333526186264,
        "y": 35.28571855143208,
        "radius": 21
    },
    {
        "x": 500.2118535603173,
        "y": 14.866732485975263,
        "radius": 21
    },
    {
        "x": 535.9742410872482,
        "y": 26.8374585767899,
        "radius": 21
    },
    {
        "x": 523.4431415472446,
        "y": 66.45991495565497,
        "radius": 21
    },
    {
        "x": 557.7544376671127,
        "y": 76.71457503380564,
        "radius": 21
    },
    {
        "x": 300.52396700827273,
        "y": 37.141280174714936,
        "radius": 21
    },
    {
        "x": 202.9976223413741,
        "y": 43.78342175923021,
        "radius": 21
    },
    {
        "x": 238.9270339268769,
        "y": 58.019080502954104,
        "radius": 21
    },
    {
        "x": 225.2788910969545,
        "y": 100.45533617497392,
        "radius": 21
    },
    {
        "x": 168.07353188290918,
        "y": 121.01353613766821,
        "radius": 21
    },
    {
        "x": 159.52335880078772,
        "y": 166.72212365224325,
        "radius": 21
    },
    {
        "x": 246.51971585494078,
        "y": 149.00545307679855,
        "radius": 21
    },
    {
        "x": 213.12013932025735,
        "y": 139.13985945612075,
        "radius": 21
    },
    {
        "x": 304.0974228322923,
        "y": 127.50932001638611,
        "radius": 21
    },
    {
        "x": 627.7270478493474,
        "y": 139.47948268043768,
        "radius": 21
    },
    {
        "x": 585.3389998752283,
        "y": 133.4559555414772,
        "radius": 21
    },
    {
        "x": 456.36524225642495,
        "y": 138.74336747670654,
        "radius": 21
    },
    {
        "x": 489.9318428496804,
        "y": 150.8738937502936,
        "radius": 21
    },
    {
        "x": 443.29477089454315,
        "y": 177.03882430038058,
        "radius": 21
    },
    {
        "x": 479.96887800665843,
        "y": 189.39861684866804,
        "radius": 21
    },
    {
        "x": 528.0953410150207,
        "y": 159.4819539077083,
        "radius": 21
    },
    {
        "x": 547.8084750736195,
        "y": 217.2516016039426,
        "radius": 21
    },
    {
        "x": 587.5517890584326,
        "y": 235.30845883046726,
        "radius": 21
    },
    {
        "x": 626.383383458061,
        "y": 252.97624959951906,
        "radius": 21
    },
    {
        "x": 683.4600182596965,
        "y": 224.68531858037878,
        "radius": 21
    },
    {
        "x": 719.2224057866274,
        "y": 236.65604467119337,
        "radius": 21
    },
    {
        "x": 608.0479182898063,
        "y": 285.73444192772837,
        "radius": 21
    },
    {
        "x": 573.4025740527943,
        "y": 270.9499165437592,
        "radius": 21
    },
    {
        "x": 539.0912779329263,
        "y": 260.69525646560845,
        "radius": 21
    },
    {
        "x": 528.2165935047198,
        "y": 298.83091310651,
        "radius": 21
    },
    {
        "x": 435.04352305900943,
        "y": 310.62125272901716,
        "radius": 21
    },
    {
        "x": 467.32605630377407,
        "y": 323.30064564284953,
        "radius": 21
    },
    {
        "x": 508.2247132246681,
        "y": 333.07590517268284,
        "radius": 21
    },
    {
        "x": 547.8010031509091,
        "y": 348.86782974629824,
        "radius": 21
    },
    {
        "x": 584.1027624997181,
        "y": 362.1655553923039,
        "radius": 21
    },
    {
        "x": 603.4435487950107,
        "y": 420.8731361862564,
        "radius": 21
    },
    {
        "x": 529.9666101583704,
        "y": 388.4208200332354,
        "radius": 21
    },
    {
        "x": 491.09671611257977,
        "y": 376.2208276677203,
        "radius": 21
    },
    {
        "x": 459.5205787482653,
        "y": 367.1333669619884,
        "radius": 21
    },
    {
        "x": 474.1740427052256,
        "y": 416.1628844121303,
        "radius": 21
    },
    {
        "x": 515.2397236846915,
        "y": 428.2030765948729,
        "radius": 21
    },
    {
        "x": 586.8932231509629,
        "y": 459.8772598329483,
        "radius": 21
    },
    {
        "x": 608.5968204385026,
        "y": 520.6899730970376,
        "radius": 21
    },
    {
        "x": 574.8631957866752,
        "y": 506.29451417054116,
        "radius": 21
    },
    {
        "x": 540.9625470762758,
        "y": 489.63412259113557,
        "radius": 21
    },
    {
        "x": 507.06189836587635,
        "y": 472.97373101172997,
        "radius": 21
    },
    {
        "x": 468.3590283786576,
        "y": 463.0386712991242,
        "radius": 21
    },
    {
        "x": 427.8710188672323,
        "y": 446.8576802680359,
        "radius": 21
    },
    {
        "x": 336.5596872380532,
        "y": 453.95835440195196,
        "radius": 21
    },
    {
        "x": 375.2242575791096,
        "y": 469.3612125180945,
        "radius": 21
    },
    {
        "x": 400.2406850902436,
        "y": 527.2003263062568,
        "radius": 21
    },
    {
        "x": 440.0222987212187,
        "y": 539.7893851292447,
        "radius": 21
    },
    {
        "x": 446.9160566915432,
        "y": 495.567597352633,
        "radius": 21
    },
    {
        "x": 488.6881335514595,
        "y": 511.19972174347595,
        "radius": 21
    },
    {
        "x": 561.6257003662214,
        "y": 542.3250383413058,
        "radius": 21
    },
    {
        "x": 597.5551119517243,
        "y": 556.5606970850299,
        "radius": 21
    },
    {
        "x": 642.9720087482712,
        "y": 208.5043275492905,
        "radius": 21
    },
    {
        "x": 607.9543167479528,
        "y": 194.65773526303943,
        "radius": 21
    },
    {
        "x": 571.3185092819997,
        "y": 176.83014431121515,
        "radius": 21
    },
    {
        "x": 703.5837997277639,
        "y": 276.049234775358,
        "radius": 21
    },
    {
        "x": 261.8338041234783,
        "y": 338.71092928093344,
        "radius": 21
    },
    {
        "x": 296.85149612379655,
        "y": 352.55752156718444,
        "radius": 21
    },
    {
        "x": 285.3991402275496,
        "y": 394.8339770564317,
        "radius": 21
    },
    {
        "x": 274.0233836236272,
        "y": 426.1748357386054,
        "radius": 21
    },
    {
        "x": 237.0152283943679,
        "y": 409.2851778844994,
        "radius": 21
    },
    {
        "x": 260.04119267656097,
        "y": 464.08122610480655,
        "radius": 21
    },
    {
        "x": 225.395848439549,
        "y": 449.2967007208373,
        "radius": 21
    },
    {
        "x": 131.7643006113895,
        "y": 239.33203863401803,
        "radius": 21
    },
    {
        "x": 343.22794247850834,
        "y": 233.05095169949928,
        "radius": 21
    },
    {
        "x": 325.18822578123553,
        "y": 275.8068077370639,
        "radius": 21
    },
    {
        "x": 254.65176960488287,
        "y": 241.31882520583403,
        "radius": 21
    },
    {
        "x": 214.7031319153358,
        "y": 226.4648337299368,
        "radius": 21
    },
    {
        "x": 178.1960488617924,
        "y": 216.36997383455864,
        "radius": 21
    },
    {
        "x": 241.17065083353265,
        "y": 286.02001353076304,
        "radius": 21
    }
]