[
    {
        "x": 345.48307843146563,
        "y": 635.6586734953844,
        "radius": 18
    },
    {
        "x": 387.5283550071125,
        "y": 643.4860852803927,
        "radius": 18
    },
    {
        "x": 431.38425548460145,
        "y": 649.805909740332,
        "radius": 18
    },
    {
        "x": 474.32117726510694,
        "y": 651.8863225571137,
        "radius": 18
    },
    {
        "x": 517.9648415713041,
        "y": 655.1347754560522,
        "radius": 18
    },
    {
        "x": 561.5912786985805,
        "y": 655.7211578190271,
        "radius": 18
    },
    {
        "x": 602.9783866951691,
        "y": 659.987694504379,
        "radius": 18
    },
    {
        "x": 648.0296969003546,
        "y": 660.2325715631189,
        "radius": 18
    },
    {
        "x": 697.3373258831718,
        "y": 659.5026348569055,
        "radius": 18
    },
    {
        "x": 748.1303319878298,
        "y": 662.1648532498475,
        "radius": 18
    },
    {
        "x": 795.802727956558,
        "y": 663.6708513629163,
        "radius": 18
    },
    {
        "x": 299.42421596496047,
        "y": 587.9941482322836,
        "radius": 18
    },
    {
        "x": 341.5416728926457,
        "y": 592.0987505505873,
        "radius": 18
    },
    {
        "x": 427.82682445018224,
        "y": 595.8896985488622,
        "radius": 18
    },
    {
        "x": 839.9630329843781,
        "y": 654.1713989788634,
        "radius": 18
    },
    {
        "x": 885.05336954508,
        "y": 661.4165153771153,
        "radius": 18
    },
    {
        "x": 469.6637842458582,
        "y": 593.6341274333295,
        "radius": 18
    },
    {
        "x": 928.0930637994992,
        "y": 656.5580610328274,
        "radius": 18
    },
    {
        "x": 559.6876911357979,
        "y": 604.2555069662635,
        "radius": 18
    },
    {
        "x": 600.7535875368549,
        "y": 598.9801673116635,
        "radius": 18
    },
    {
        "x": 646.2872895464733,
        "y": 602.8802805575026,
        "radius": 18
    },
    {
        "x": 298.4805811806955,
        "y": 549.8790927570953,
        "radius": 18
    },
    {
        "x": 693.2312374721238,
        "y": 601.8318145292045,
        "radius": 18
    },
    {
        "x": 340.22910661953836,
        "y": 548.1639463727546,
        "radius": 18
    },
    {
        "x": 742.6110434163149,
        "y": 604.928885613987,
        "radius": 18
    },
    {
        "x": 425.83048720528916,
        "y": 554.6905035408878,
        "radius": 18
    },
    {
        "x": 790.7888414420829,
        "y": 605.8197660667915,
        "radius": 18
    },
    {
        "x": 837.0571511310826,
        "y": 611.844590650554,
        "radius": 18
    },
    {
        "x": 470.7819882798359,
        "y": 555.2996991967377,
        "radius": 18
    },
    {
        "x": 883.2321810181361,
        "y": 605.2355592303987,
        "radius": 18
    },
    {
        "x": 601.9173100530788,
        "y": 557.9329758352508,
        "radius": 18
    },
    {
        "x": 647.0380241082103,
        "y": 561.3030115248167,
        "radius": 18
    },
    {
        "x": 558.3478081692353,
        "y": 549.515853094316,
        "radius": 18
    },
    {
        "x": 694.3450423037007,
        "y": 561.6632739963576,
        "radius": 18
    },
    {
        "x": 747.5917459415102,
        "y": 561.3465596337609,
        "radius": 18
    },
    {
        "x": 294.99505961701686,
        "y": 495.4756896950267,
        "radius": 18
    },
    {
        "x": 337.60210610265176,
        "y": 499.29710473175265,
        "radius": 18
    },
    {
        "x": 789.6435902521168,
        "y": 562.1186633558497,
        "radius": 18
    },
    {
        "x": 381.2498825712976,
        "y": 498.75662060556624,
        "radius": 18
    },
    {
        "x": 424.51160064402575,
        "y": 498.353665235151,
        "radius": 18
    },
    {
        "x": 834.6900679507219,
        "y": 556.4742261058357,
        "radius": 18
    },
    {
        "x": 465.5884878949016,
        "y": 499.7400762986682,
        "radius": 18
    },
    {
        "x": 877.960936319038,
        "y": 556.9024142406477,
        "radius": 18
    },
    {
        "x": 923.7691522495954,
        "y": 556.6289806027611,
        "radius": 18
    },
    {
        "x": 511.3221975759772,
        "y": 499.90817918149827,
        "radius": 18
    },
    {
        "x": 559.2371484245573,
        "y": 502.6982538073762,
        "radius": 18
    },
    {
        "x": 602.7847289553749,
        "y": 503.00991840417083,
        "radius": 18
    },
    {
        "x": 649.356893169394,
        "y": 504.90837800914363,
        "radius": 18
    },
    {
        "x": 290.306177687596,
        "y": 455.34538247851356,
        "radius": 18
    },
    {
        "x": 338.7445399376296,
        "y": 455.19751839415534,
        "radius": 18
    },
    {
        "x": 694.6079651122081,
        "y": 503.28046645857415,
        "radius": 18
    },
    {
        "x": 378.8903222104516,
        "y": 453.0119643820764,
        "radius": 18
    },
    {
        "x": 741.0068694247548,
        "y": 503.02313551248136,
        "radius": 18
    },
    {
        "x": 787.9471661150187,
        "y": 510.603692599185,
        "radius": 18
    },
    {
        "x": 422.74115461573103,
        "y": 453.4634676700534,
        "radius": 18
    },
    {
        "x": 832.7982368831856,
        "y": 509.9175193580192,
        "radius": 18
    },
    {
        "x": 466.2087068107371,
        "y": 454.8056553491227,
        "radius": 18
    },
    {
        "x": 512.407724238328,
        "y": 454.81893823233935,
        "radius": 18
    },
    {
        "x": 880.191846270952,
        "y": 511.0697394813912,
        "radius": 18
    },
    {
        "x": 926.1028427273719,
        "y": 508.8363935320698,
        "radius": 18
    },
    {
        "x": 558.1982104873141,
        "y": 455.0394934249237,
        "radius": 18
    },
    {
        "x": 603.3214507642303,
        "y": 457.4323962021014,
        "radius": 18
    },
    {
        "x": 648.645163881549,
        "y": 455.56063281243024,
        "radius": 18
    },
    {
        "x": 693.2015371041139,
        "y": 458.2498114421405,
        "radius": 18
    },
    {
        "x": 290.31014157924585,
        "y": 400.09332604214126,
        "radius": 18
    },
    {
        "x": 335.93943288380353,
        "y": 402.033713313988,
        "radius": 18
    },
    {
        "x": 740.6842953524493,
        "y": 456.2881593030573,
        "radius": 18
    },
    {
        "x": 380.0870594639589,
        "y": 401.83589617304835,
        "radius": 18
    },
    {
        "x": 835.832670747759,
        "y": 452.92798533525223,
        "radius": 18
    },
    {
        "x": 465.35069648312833,
        "y": 398.6865096567181,
        "radius": 18
    },
    {
        "x": 508.2852269423312,
        "y": 399.9163323879799,
        "radius": 18
    },
    {
        "x": 883.5815291480842,
        "y": 451.6366318588888,
        "radius": 18
    },
    {
        "x": 556.1860284144145,
        "y": 399.3709609982554,
        "radius": 18
    },
    {
        "x": 288.9932288572327,
        "y": 358.9700572755515,
        "radius": 18
    },
    {
        "x": 931.096808922413,
        "y": 449.53591493219807,
        "radius": 18
    },
    {
        "x": 599.805116735633,
        "y": 400.66020897058576,
        "radius": 18
    },
    {
        "x": 333.3057566657793,
        "y": 356.69046856945005,
        "radius": 18
    },
    {
        "x": 645.1420007627377,
        "y": 400.68300785308855,
        "radius": 18
    },
    {
        "x": 376.6021445594869,
        "y": 353.8576343881998,
        "radius": 18
    },
    {
        "x": 737.5120096733526,
        "y": 401.22733798925566,
        "radius": 18
    },
    {
        "x": 695.1367263973011,
        "y": 399.5682370674254,
        "radius": 18
    },
    {
        "x": 838.0160378892704,
        "y": 411.070844813013,
        "radius": 18
    },
    {
        "x": 465.04512005194374,
        "y": 355.6728355347391,
        "radius": 18
    },
    {
        "x": 885.521895331967,
        "y": 409.2494382577446,
        "radius": 18
    },
    {
        "x": 555.4888046475892,
        "y": 355.80143772209505,
        "radius": 18
    },
    {
        "x": 932.6814614797278,
        "y": 408.0440073549376,
        "radius": 18
    },
    {
        "x": 597.7173718867655,
        "y": 353.7771864553902,
        "radius": 18
    },
    {
        "x": 290.65996630257143,
        "y": 304.09892521683565,
        "radius": 18
    },
    {
        "x": 645.672875075159,
        "y": 356.2455542170284,
        "radius": 18
    },
    {
        "x": 689.7258476844752,
        "y": 356.4515994239022,
        "radius": 18
    },
    {
        "x": 377.1692671616215,
        "y": 308.1685441024492,
        "radius": 18
    },
    {
        "x": 333.61311918661227,
        "y": 306.45414012116464,
        "radius": 18
    },
    {
        "x": 738.2972885667269,
        "y": 356.699166389175,
        "radius": 18
    },
    {
        "x": 792.5863928181857,
        "y": 355.02022908508303,
        "radius": 18
    },
    {
        "x": 420.9221056046101,
        "y": 303.81779563388017,
        "radius": 18
    },
    {
        "x": 509.8729163164078,
        "y": 301.275218635357,
        "radius": 18
    },
    {
        "x": 555.5465679782824,
        "y": 301.909471468901,
        "radius": 18
    },
    {
        "x": 288.34249630800207,
        "y": 263.685293903777,
        "radius": 18
    },
    {
        "x": 932.3425482951374,
        "y": 356.4197259760903,
        "radius": 18
    },
    {
        "x": 333.18697921296496,
        "y": 263.4224087457837,
        "radius": 18
    },
    {
        "x": 599.7819732803052,
        "y": 300.95979007057656,
        "radius": 18
    },
    {
        "x": 644.1483318106982,
        "y": 304.20925935920957,
        "radius": 18
    },
    {
        "x": 377.7220249450454,
        "y": 260.78187847988096,
        "radius": 18
    },
    {
        "x": 687.7968317869113,
        "y": 304.12680809319056,
        "radius": 18
    },
    {
        "x": 739.7568510890717,
        "y": 300.03178635185355,
        "radius": 18
    },
    {
        "x": 835.4437766637938,
        "y": 310.72083024140755,
        "radius": 18
    },
    {
        "x": 513.2586730411945,
        "y": 256.64578800001686,
        "radius": 18
    },
    {
        "x": 558.1261666677115,
        "y": 258.18973245046055,
        "radius": 18
    },
    {
        "x": 882.6558392262484,
        "y": 305.66706073703335,
        "radius": 18
    },
    {
        "x": 597.0189322568026,
        "y": 259.57564282811114,
        "radius": 18
    },
    {
        "x": 941.0936675357962,
        "y": 306.8860257992764,
        "radius": 18
    },
    {
        "x": 332.83550111276656,
        "y": 206.55890165999887,
        "radius": 18
    },
    {
        "x": 376.88212409349194,
        "y": 209.26235135552372,
        "radius": 18
    },
    {
        "x": 737.0139780958145,
        "y": 260.990115170857,
        "radius": 18
    },
    {
        "x": 785.2038589531107,
        "y": 258.99769363536717,
        "radius": 18
    },
    {
        "x": 420.4034476866211,
        "y": 205.61966857506474,
        "radius": 18
    },
    {
        "x": 834.1211835003146,
        "y": 257.7559580488685,
        "radius": 18
    },
    {
        "x": 878.6603425719526,
        "y": 264.8166297760758,
        "radius": 18
    },
    {
        "x": 466.74023709473715,
        "y": 203.86796894215655,
        "radius": 18
    },
    {
        "x": 156.70196699992107,
        "y": 160.80736781611162,
        "radius": 18
    },
    {
        "x": 196.42994692580487,
        "y": 159.52883572860952,
        "radius": 18
    },
    {
        "x": 509.8549602838807,
        "y": 203.56862879876024,
        "radius": 18
    },
    {
        "x": 555.2633235247749,
        "y": 202.1880880534333,
        "radius": 18
    },
    {
        "x": 937.7881109654822,
        "y": 256.6873777984602,
        "radius": 18
    },
    {
        "x": 601.4795091573194,
        "y": 202.33218121069888,
        "radius": 18
    },
    {
        "x": 646.2967780804291,
        "y": 205.06471085847812,
        "radius": 18
    },
    {
        "x": 331.57536168196293,
        "y": 161.67207662242362,
        "radius": 18
    },
    {
        "x": 694.9957621021642,
        "y": 205.1934447311204,
        "radius": 18
    },
    {
        "x": 375.9296731800632,
        "y": 157.55231444777277,
        "radius": 18
    },
    {
        "x": 420.55238019706144,
        "y": 159.02064788810253,
        "radius": 18
    },
    {
        "x": 741.3275720568599,
        "y": 204.89080680277607,
        "radius": 18
    },
    {
        "x": 464.80675025342714,
        "y": 160.0973026431014,
        "radius": 18
    },
    {
        "x": 153.29003616410444,
        "y": 113.48149959289519,
        "radius": 18
    },
    {
        "x": 788.8087192233734,
        "y": 205.12894572803486,
        "radius": 18
    },
    {
        "x": 835.9693449588926,
        "y": 213.3389628022748,
        "radius": 18
    },
    {
        "x": 880.9356550329165,
        "y": 215.0001225458297,
        "radius": 18
    },
    {
        "x": 196.2453531999297,
        "y": 116.10745696927613,
        "radius": 18
    },
    {
        "x": 509.1695397348915,
        "y": 156.46050625863586,
        "radius": 18
    },
    {
        "x": 555.9427129989749,
        "y": 158.85055808960124,
        "radius": 18
    },
    {
        "x": 933.8963266377166,
        "y": 212.07749619942382,
        "radius": 18
    },
    {
        "x": 601.3543629376982,
        "y": 158.15836333698257,
        "radius": 18
    },
    {
        "x": 644.1879548527129,
        "y": 160.16373046499325,
        "radius": 18
    },
    {
        "x": 330.8830057757157,
        "y": 105.29233101714694,
        "radius": 18
    },
    {
        "x": 695.5341515881876,
        "y": 159.29948686603618,
        "radius": 18
    },
    {
        "x": 741.0627555068247,
        "y": 159.64693057796,
        "radius": 18
    },
    {
        "x": 374.011552292755,
        "y": 105.34094244770024,
        "radius": 18
    },
    {
        "x": 787.06773034355,
        "y": 162.8960839889885,
        "radius": 18
    },
    {
        "x": 421.5158964773302,
        "y": 103.30837599142909,
        "radius": 18
    },
    {
        "x": 835.7542758581674,
        "y": 161.7638271819382,
        "radius": 18
    },
    {
        "x": 884.0125072889382,
        "y": 162.0185764246757,
        "radius": 18
    },
    {
        "x": 466.30681949746054,
        "y": 100.42201572827938,
        "radius": 18
    },
    {
        "x": 933.5459132241576,
        "y": 162.53077991052714,
        "radius": 18
    },
    {
        "x": 511.60236204433244,
        "y": 102.05978054599673,
        "radius": 18
    },
    {
        "x": 604.1876958594257,
        "y": 98.4460759464626,
        "radius": 18
    },
    {
        "x": 649.7174425113444,
        "y": 104.67388866945019,
        "radius": 18
    },
    {
        "x": 701.2422905301994,
        "y": 103.28286154178245,
        "radius": 18
    },
    {
        "x": 744.2785544004398,
        "y": 106.3426344244731,
        "radius": 18
    },
    {
        "x": 792.553991904547,
        "y": 108.00175492845196,
        "radius": 18
    },
    {
        "x": 846.5647054073954,
        "y": 112.38222304683367,
        "radius": 18
    },
    {
        "x": 887.2672744071795,
        "y": 115.74717306187678,
        "radius": 18
    },
    {
        "x": 933.5577254887025,
        "y": 118.3502428035572,
        "radius": 18
    },
    {
        "x": 560.0282625771731,
        "y": 100.87328769942877,
        "radius": 18
    },
    {
        "x": 468.1611239651385,
        "y": 257.54309603287004,
        "radius": 18
    },
    {
        "x": 431.5353482884476,
        "y": 259.4279185923493,
        "radius": 18
    },
    {
        "x": 464.40341229394414,
        "y": 305.48972889688014,
        "radius": 18
    },
    {
        "x": 510.432420138774,
        "y": 358.4645383521353,
        "radius": 18
    },
    {
        "x": 512.2426905973582,
        "y": 559.7049987990017,
        "radius": 18
    },
    {
        "x": 514.4167976135654,
        "y": 601.421581337389,
        "radius": 18
    },
    {
        "x": 382.55386348947695,
        "y": 555.4850315737607,
        "radius": 18
    },
    {
        "x": 384.01818013610364,
        "y": 595.0811901848989,
        "radius": 18
    },
    {
        "x": 839.9421269543601,
        "y": 356.63338726429396,
        "radius": 18
    },
    {
        "x": 882.7979529566737,
        "y": 360.6803833922163,
        "radius": 18
    },
    {
        "x": 786.9822255958198,
        "y": 302.677397345716,
        "radius": 18
    },
    {
        "x": 686.5263240330454,
        "y": 263.18329315880504,
        "radius": 18
    },
    {
        "x": 647.9113458852299,
        "y": 257.7167162917212,
        "radius": 18
    },
    {
        "x": 419.08151910591744,
        "y": 361.66819716693436,
        "radius": 18
    },
    {
        "x": 418.70574910052994,
        "y": 399.9938908580217,
        "radius": 18
    }
]